myVaillant/__init__.py
myVaillant/api.py
myVaillant/const.py
myVaillant/enums.py
myVaillant/export.py
myVaillant/http_client.py
myVaillant/models.py
myVaillant/py.typed
myVaillant/report.py
myVaillant/sample.py
myVaillant/utils.py
myVaillant/tests/__init__.py
myVaillant/tests/conftest.py
myVaillant/tests/find_countries.py
myVaillant/tests/generate_test_data.py
myVaillant/tests/run_function_test.py
myVaillant/tests/test_api.py
myVaillant/tests/test_countries.py
myVaillant/tests/test_export.py
myVaillant/tests/test_generate_test_data.py
myVaillant/tests/test_models.py
myVaillant/tests/test_sample.py
myVaillant/tests/test_utils.py
myVaillant/tests/update_sample.py
myVaillant/tests/utils.py
myVaillant/tests/data/ambisense2.yaml
myVaillant/tests/data/no_cooling.yaml
myVaillant/tests/data/vrc700_dhw.yaml
myVaillant/tests/data/vrc700_mpc_rts.yaml
myVaillant/tests/data/vrc700_ventilation.yaml
myVaillant/tests/data/ambisense/homes.json
myVaillant/tests/data/ambisense/fc9ac9ea562b2a82a48708045a7c628e33c0de4b/connection_status.json
myVaillant/tests/data/ambisense/fc9ac9ea562b2a82a48708045a7c628e33c0de4b/control_identifier.json
myVaillant/tests/data/ambisense/fc9ac9ea562b2a82a48708045a7c628e33c0de4b/current_system.json
myVaillant/tests/data/ambisense/fc9ac9ea562b2a82a48708045a7c628e33c0de4b/diagnostic_trouble_codes.json
myVaillant/tests/data/ambisense/fc9ac9ea562b2a82a48708045a7c628e33c0de4b/mpc.json
myVaillant/tests/data/ambisense/fc9ac9ea562b2a82a48708045a7c628e33c0de4b/rbr.json
myVaillant/tests/data/ambisense/fc9ac9ea562b2a82a48708045a7c628e33c0de4b/rooms.json
myVaillant/tests/data/ambisense/fc9ac9ea562b2a82a48708045a7c628e33c0de4b/rts.json
myVaillant/tests/data/ambisense/fc9ac9ea562b2a82a48708045a7c628e33c0de4b/system.json
myVaillant/tests/data/ambisense/fc9ac9ea562b2a82a48708045a7c628e33c0de4b/time_zone.json
myVaillant/tests/data/heatpump_cooling/homes.json
myVaillant/tests/data/heatpump_cooling/d6f61ab2a0ad4fb8d70e8b7c4faade70f6d2e9fe/connection_status.json
myvaillant-1.0.0.dist-info/METADATA
myvaillant-1.0.0.dist-info/WHEEL
myvaillant-1.0.0.dist-info/licenses/LICENSE
myvaillant-1.0.0.dist-info/RECORD
